recsys/__init__.py
recsys/datasets/__init__.py
recsys/datasets/datasets.py
recsys/datasets/utils.py
recsys/external_datasets/__init__.py
recsys/external_datasets/base.py
recsys/external_datasets/movielens.py
recsys/external_datasets/netflix.py
recsys/layers/__init__.py
recsys/layers/features.py
recsys/layers/utils.py
recsys/models/__init__.py
recsys/models/base.py
recsys/models/trainers.py
recsys/models/utils.py
recsys/models/scoring/__init__.py
recsys/models/scoring/ncf.py
recsys/models/scoring/nes.py
test/__init__.py
test/fixtures.py
test/test_datasets.py
test/test_scoring.py
RecSys-0.0.1a3.dist-info/LICENSE
RecSys-0.0.1a3.dist-info/METADATA
RecSys-0.0.1a3.dist-info/WHEEL
RecSys-0.0.1a3.dist-info/top_level.txt
RecSys-0.0.1a3.dist-info/zip-safe
RecSys-0.0.1a3.dist-info/RECORD
