Metadata-Version: 2.1
Name: RecSys
Version: 0.0.1a3
Summary: Lightweight pytorch library to build recommender systems.
Author: Jaime Ferrando Huertas
Author-email: fhjaime96@gmail.com
Requires-Python: >=3.7
License-File: LICENSE
Requires-Dist: torch
Requires-Dist: pytorch-lightning
Requires-Dist: scikit-learn
Requires-Dist: protobuf
Requires-Dist: pandas
